[{"id":"8b8d27a8-363b-4860-94ba-8a285651db6c","title":"reel Beast","description":"4 rulemanes manija izq o der","price":1200,"thumbnail":"imagenREEL","code":"cod 1","stock":15,"status":true,"category":"pesca"},{"id":"70c91cef-8553-4272-b976-02ce63ca5e25","title":"caña de pescar","description":"2 tramos total de 1,80m","price":800,"thumbnail":"imagenCAÑA","code":"cod 2","stock":25,"status":true,"category":"pesca"},{"id":"85bd1adc-eb6a-4d15-b045-31f60a106b09","title":"caña de pescar Fish","description":"1 tramo de 2.10","price":12320,"thumbnail":"imagenCañaFish","code":"cod 3","stock":24,"status":true,"category":"pesca"},{"id":"ab248a19-72dd-48d8-a721-ea4799be7e66","title":"Carpa camuflada","description":"Carpa para 4 personas","price":50000,"thumbnail":"imagenCarpa","code":"cod 4","stock":12,"status":true,"category":"camping"},{"id":"503d99cb-7180-4cd7-8bae-935c746aeb44","title":"Termo Sifon","description":"2.5 litros de acero inoxidable","price":32000,"thumbnail":"imagenTermo.jpg","code":"cod 5","stock":32,"status":"true","category":"camping"},{"id":"4e3a1431-fcb0-40fb-8c3a-82606e19c329","title":"prueba1","description":"ACTUALIZANDO DESDE POSTMAN","price":32000,"thumbnail":"imagenprueba.jpg","code":"cod 5","stock":32,"status":"true","category":"camping"}]